[
  {
    "title": "乌总统签署法令 制裁4名前政府官员",
    "content": "【乌总统签署法令 制裁4名前政府官员】财联社4月12日电，当地时间4月12日，乌克兰总统泽连斯基签署法令，对乌前总统亚努科维奇任期内的前第一副总理谢尔盖·阿尔布佐夫，前国家安全和国防委员会秘书、前总统办公厅主任安德烈·克柳耶夫等4人实施制裁。",
    "date": "2025-04-12",
    "time": "17:55:06",
    "datetime": "2025-04-12 17:55:06",
    "fetch_time": "2025-04-12 18:02:03",
    "hash": "32369af7eccb61699e6f2cd7cd43f558"
  },
  {
    "title": "2025年度总票房破250亿 哪吒2票房占比超六成",
    "content": "【2025年度总票房破250亿 哪吒2票房占比超六成】财联社4月12日电，据灯塔专业版数据，截至4月12日17时38分，2025年度大盘票房(含预售)突破250亿，《哪吒之魔童闹海》以60.8%的票房占比断层领跑。",
    "date": "2025-04-12",
    "time": "17:52:53",
    "datetime": "2025-04-12 17:52:53",
    "fetch_time": "2025-04-12 18:02:03",
    "hash": "eed60c87642b9f4a1560aa22e15b5b99"
  },
  {
    "title": "以军持续分割加沙 控制第二条“费城走廊”并包围拉法",
    "content": "【以军持续分割加沙 控制第二条“费城走廊”并包围拉法】财联社4月12日电，以色列国防军当地时间12日发表声明称，在过去的一天，以军第36师已控制加沙地带南部的“莫拉格走廊”，切断了巴勒斯坦伊斯兰抵抗运动（哈马斯）拉法旅与汗尤尼斯旅之间的联系。在过去一周多的时间里，以军在“莫拉格走廊”打死多名巴勒斯坦武装人员，拆除地下隧道与军事设施，并完成对拉法市的包围。据报道，目前，以军第36师控制着“莫拉格走廊”，加沙师则在“费城走廊”展开行动。据悉，以军接下来将进入拉法，打击那里剩余的哈马斯武装人员。约两周前，以军已向拉法当地平民发布了撤离警告。",
    "date": "2025-04-12",
    "time": "17:50:07",
    "datetime": "2025-04-12 17:50:07",
    "fetch_time": "2025-04-12 17:52:02",
    "hash": "af70da05247cc86e7fa8b9084947968f"
  },
  {
    "title": "乘联会崔东树：3月全国汽车市场走势分化 呈现乘强商弱的走势",
    "content": "【乘联会崔东树：3月全国汽车市场走势分化 呈现乘强商弱的走势】财联社4月12日电，乘联会秘书长崔东树发文称，3月全国汽车市场走势分化，呈现乘强商弱的走势。2025年1月底新一轮补贴政策落实，狭义乘用车2—3月零售最终高于此前预期。两新政策发布前，市场热度较低，1月消费者多处于一种观望与等待的状态，2—3月市场热度快速增长，消费类乘用车产品在春节前的消费保持较好态势，而商用车市场出现结构性增长特征。去年的商用车渠道库存偏高，今年3月的商用车走势分化，轻卡、微客和大中客的新能源类别增长较强。",
    "date": "2025-04-12",
    "time": "17:29:57",
    "datetime": "2025-04-12 17:29:57",
    "fetch_time": "2025-04-12 17:32:01",
    "hash": "53928d4359c6edf7cd2fb3aca48b5f15"
  },
  {
    "title": "俄外交官：美特使在乌划分控制区冻结冲突方案或致冲突升级",
    "content": "【俄外交官：美特使在乌划分控制区冻结冲突方案或致冲突升级】财联社4月12日电，俄罗斯外交部无任所大使米罗什尼克向媒体表示，美国乌克兰问题特使凯洛格提出的，有关将乌克兰分割成不同控制区的想法，是冻结冲突的方案之一，这有可能导致冲突新的升级。俄罗斯外交部发言人扎哈罗娃曾表示，俄罗斯无法接受冻结俄乌冲突或暂时停火，因为这将被西方用来加强乌克兰的军事力量。",
    "date": "2025-04-12",
    "time": "17:28:03",
    "datetime": "2025-04-12 17:28:03",
    "fetch_time": "2025-04-12 17:32:01",
    "hash": "671e8b0ad34b6d0fc5786fb4a075d5d0"
  },
  {
    "title": "受大风影响 福建沿海和琼州海峡这些客运航线全线停航",
    "content": "【受大风影响 福建沿海和琼州海峡这些客运航线全线停航】财联社4月12日电，受大风影响，截至16时，福建沿海除了1条市民航线外，其余77条客渡运航线、205艘客渡船全部停航，其中4条两岸“小三通”客运航线全部停航。97个水上施工作业项目全部停工。根据气象台发布的最新气象灾害预警信号，琼州海峡航线4月12日17时30分起，风力逐渐增大到8级以上。经海峡各部门协商决定，所有客滚船于17时30分起全线停航。",
    "date": "2025-04-12",
    "time": "17:24:55",
    "datetime": "2025-04-12 17:24:55",
    "fetch_time": "2025-04-12 17:32:01",
    "hash": "c9f84624b1186804adb7862bb92cddaf"
  },
  {
    "title": "河南省发文支持家装厨卫“焕新” 每套房最高补贴2万元",
    "content": "【河南省发文支持家装厨卫“焕新” 每套房最高补贴2万元】财联社4月12日电，河南省商务厅等7部门发布《关于做好2025年家装厨卫“焕新”有关工作的通知》。其中提出，对个人消费者购买智能马桶、智能门锁、智能晾衣架、智能沙发（含电动按摩椅）等家居产品，按最终销售价格（剔除所有折扣和优惠后的价格）的15%给予补贴，单件补贴不超过1500元。加大对个人消费者在开展旧房装修、厨卫等局部改造过程中购置所用物品和材料的补贴力度，在风险可控前提下，鼓励有条件的地市探索以装修合同为依据实施补贴，每套房补贴最高不超过2万元。",
    "date": "2025-04-12",
    "time": "17:13:30",
    "datetime": "2025-04-12 17:13:30",
    "fetch_time": "2025-04-12 17:13:35",
    "hash": "42e73a07eeb49b93ff0656135db0d096"
  },
  {
    "title": "哈马斯高级领导人赴开罗进行加沙停火谈判",
    "content": "【哈马斯高级领导人赴开罗进行加沙停火谈判】财联社4月12日电，当地时间12日，一名巴勒斯坦伊斯兰抵抗运动（哈马斯）官员称，哈马斯的高级领导人今天正前往埃及首都开罗，将与斡旋方埃及就加沙被扣押人员交换与停火问题展开会谈。该官员表示，哈马斯希望这次会谈能够在结束冲突、停止以军侵略以及确保以军完全撤出加沙方面取得实质性进展。12日稍早时，有以色列媒体援引两名以色列官员表态称，以方在加沙停火协议的协商中降低了对释放被扣押人员数量等方面的要求。",
    "date": "2025-04-12",
    "time": "17:11:42",
    "datetime": "2025-04-12 17:11:42",
    "fetch_time": "2025-04-12 17:13:35",
    "hash": "50a6abc8c4f9c131b369d3eeddc59118"
  },
  {
    "title": "自然资源部北海区海洋预报台发布海浪黄色警报",
    "content": "【自然资源部北海区海洋预报台发布海浪黄色警报】财联社4月12日电，自然资源部北海区海洋预报台根据《自然资源部北海局海洋灾害应急执行预案》发布海浪黄色警报。受较强冷空气和气旋共同影响，预计12日夜间至13日白天，渤海和黄海将出现3.0米到4.5米的大浪到巨浪。山东北部和东部沿海将出现3.0米到3.8米的大浪，近岸海域警报级别为黄色；河北和辽宁南部沿海将出现2.0米到3.0米的中浪到大浪，近岸海域警报级别为蓝色。预计13日夜间至14日白天，渤海和黄海将出现3.0米到5.0米的大浪到巨浪。辽宁南部、山东北部和东部沿海将出现2.5米到3.4米的大浪，近岸海域警报级别为蓝色。",
    "date": "2025-04-12",
    "time": "17:00:58",
    "datetime": "2025-04-12 17:00:58",
    "fetch_time": "2025-04-12 17:02:53",
    "hash": "704925008ce3bc4ca5312c8f053f488a"
  },
  {
    "title": "全国人大常委会副委员长洛桑江村率团访问韩国",
    "content": "【全国人大常委会副委员长洛桑江村率团访问韩国】财联社4月12日电，应韩国国会邀请，全国人大常委会副委员长洛桑江村4月10日至12日率全国人大代表团访问韩国，分别与韩国会议长禹元植、副议长李学永、韩中议员联盟会长金太年会见会谈。洛桑江村积极评价建交30多年来中韩关系发展成果，表示中韩是搬不走的近邻和分不开的伙伴，中方重视发展中韩关系，对韩政策保持连续性稳定性。中方愿同韩方深化各领域交流合作，加强立法机构交往，推动中韩战略合作伙伴关系健康稳定向前发展。韩方表示，韩中是密不可分的合作伙伴，韩方高度重视发展韩中战略合作伙伴关系，愿同中方加强高层交往和立法机构交流，活跃开展经贸、人文等各领域合作，携手实现更好发展。韩方重申尊重一个中国立场。",
    "date": "2025-04-12",
    "time": "16:50:58",
    "datetime": "2025-04-12 16:50:58",
    "fetch_time": "2025-04-12 17:02:53",
    "hash": "cfd2536c8f8a6e7ff2789e3410ac00a6"
  },
  {
    "title": "中老铁路进出口货物超1200万吨",
    "content": "【中老铁路进出口货物超1200万吨】财联社4月12日电，从昆明海关获悉，自2021年12月中老铁路通车运营以来，经中老铁路进出口货物已超1200万吨，货值超500亿元。今年一季度，昆明海关监管验放经中老铁路进出口货物150.8万吨、货值41.9亿元，同比分别增长9.2%、17.5%，中老铁路进出口货物运输持续增长。 (新华社)",
    "date": "2025-04-12",
    "time": "16:45:42",
    "datetime": "2025-04-12 16:45:42",
    "fetch_time": "2025-04-12 17:02:53",
    "hash": "b39dc3a187507fe887a5e8514680113c"
  },
  {
    "title": "",
    "content": "财联社4月12日电，中国台湾地区金融监管机构宣布将限空令延长实施至4月18日止。",
    "date": "2025-04-12",
    "time": "16:30:33",
    "datetime": "2025-04-12 16:30:33",
    "fetch_time": "2025-04-12 17:02:53",
    "hash": "c7d689d7213b7810be0320cf588a20c6"
  },
  {
    "title": "神经保护药物丁苯酞或成阿尔茨海默病早期干预新选择",
    "content": "【神经保护药物丁苯酞或成阿尔茨海默病早期干预新选择】财联社4月12日电，发表在新一期国际学术期刊《精神病学和临床神经科学》上的一项研究表明，当前常用于治疗脑卒中的药物丁苯酞，能够显著提高阿尔茨海默病相关轻度认知障碍患者脑结构网络的全局效率。这一发现为认知障碍的早期干预提供了新思路。中国首都医科大学宣武医院魏翠柏教授团队对270名符合条件的阿尔茨海默病相关轻度认知障碍受试者开展了随机、双盲、安慰剂对照试验。研究团队指出，脑网络“失连接”是阿尔茨海默病的重要病理特征。丁苯酞可能通过恢复脑结构网络效率，缓解了这种失连接状态，从而延缓认知功能下降。揭示这一机制为治疗阿尔茨海默病开辟了新的研究方向。",
    "date": "2025-04-12",
    "time": "16:25:36",
    "datetime": "2025-04-12 16:25:36",
    "fetch_time": "2025-04-12 17:02:53",
    "hash": "55dc285f055b2dd34cca0f5ab6b820ca"
  },
  {
    "title": "北交所“920”代码亮相 今日全网测试",
    "content": "【北交所“920”代码亮相 今日全网测试】财联社4月12日电，北交所存量上市公司证券代码切换试点正式启动，首批6只股票闪亮登场，今日全网测试正式展开，为代码切换平稳落地保驾护航。据悉，920代码切换范围为2024年4月22日以前上市的存量上市公司。切换规则为，股票代码前三位变更为920，后三位保持不变。 (上证报)",
    "date": "2025-04-12",
    "time": "16:13:46",
    "datetime": "2025-04-12 16:13:46",
    "fetch_time": "2025-04-12 17:02:53",
    "hash": "10a9ff207372f8a383ca251ca3bff66a"
  },
  {
    "title": "美前副总统彭斯称关税措施是“失策”",
    "content": "【美前副总统彭斯称关税措施是“失策”】财联社4月12日电，美国前副总统迈克·彭斯日前表示，他对本届美国政府大规模加征关税措施感到担忧，称这种做法是“失策”。彭斯9日接受美国《国会山报》采访时说，尽管美国政府已撤回部分对盟友施加的最严厉关税措施，但其激进的关税政策仍可能给共和党中期选举带来潜在风险。 (新华社)",
    "date": "2025-04-12",
    "time": "16:08:44",
    "datetime": "2025-04-12 16:08:44",
    "fetch_time": "2025-04-12 17:02:53",
    "hash": "788a9b7568b99c100e6fe35a63b25c92"
  },
  {
    "title": "美国政府大幅削减对外援助 联合国人道主义机构被迫裁员20%",
    "content": "【美国政府大幅削减对外援助 联合国人道主义机构被迫裁员20%】财联社4月12日电，联合国人道主义事务协调厅在11日公开的一封信中说，由于资金遭遇“残酷削减”，尤其是美国政府大幅叫停对外援助，这一机构将裁员20%，即500多名工作人员。联合国分管人道主义事务的副秘书长兼紧急救援协调员汤姆·弗莱彻在给工作人员的一封信中写道，这一机构“面临有史以来最艰难的处境”。联合国人道主义事务协调厅目前共有约2600名工作人员在60多个国家和地区开展工作，长期为乌克兰、加沙地带、苏丹等冲突地区提供援助。",
    "date": "2025-04-12",
    "time": "16:05:47",
    "datetime": "2025-04-12 16:05:47",
    "fetch_time": "2025-04-12 17:02:53",
    "hash": "eb48939d02549527ae3b49d0d6d0b8a7"
  },
  {
    "title": "特朗普政府将赶走在美避难的阿富汗人、喀麦隆人",
    "content": "【特朗普政府将赶走在美避难的阿富汗人、喀麦隆人】财联社4月12日电，美国国土安全部发言人特里西娅·麦克劳夫林11日说，总统唐纳德·特朗普领导的联邦政府决定撤销对数以千计在美国避难阿富汗人、喀麦隆人的临时保护身份(TPS)。据估算，美国境内大约1.46万名阿富汗人的临时保护身份5月将被撤销，大约7900名喀麦隆人6月将失去这一合法身份。 (新华社)",
    "date": "2025-04-12",
    "time": "15:56:03",
    "datetime": "2025-04-12 15:56:03",
    "fetch_time": "2025-04-12 17:02:53",
    "hash": "d1ba1e87f35cce149ec051a61b741d90"
  },
  {
    "title": "伊朗外长会见阿曼外交大臣 沟通伊美间接谈判安排",
    "content": "【伊朗外长会见阿曼外交大臣 沟通伊美间接谈判安排】财联社4月12日电，当地时间12日，伊朗外长阿拉格齐与阿曼外交大臣巴德尔在阿曼举行会晤。阿拉格齐赞扬阿曼在地区问题上所持的负责任态度，并感谢阿曼举办伊朗-美国的间接谈判。阿拉格齐向阿方介绍了间接谈判的预期安排和准备情况，并提供了伊朗的谈判立场和信息，以便阿曼转交至美方。",
    "date": "2025-04-12",
    "time": "15:51:27",
    "datetime": "2025-04-12 15:51:27",
    "fetch_time": "2025-04-12 17:02:53",
    "hash": "80e5ba3afbac082de2647ed3b3b1dd23"
  },
  {
    "title": "巴西出台《商业互惠法》反制贸易壁垒",
    "content": "【巴西出台《商业互惠法》反制贸易壁垒】财联社4月12日电，据巴西通讯社报道称，巴西总统卢拉当地时间11日签署《商业互惠法》，授权联邦政府可对那些对巴西出口产品施加单边贸易壁垒的国家和经济集团采取对等反制措施。该法案将于4月14日在《联邦官方公报》上正式发布并生效。该法案在约10天前获得巴西国会通过，并成为巴西政府应对当前国际贸易紧张局势的重要立法工具。报道称，这项新法律被外界视为对美国政府近期提升关税措施的直接回应。 (中国新闻网)",
    "date": "2025-04-12",
    "time": "15:31:21",
    "datetime": "2025-04-12 15:31:21",
    "fetch_time": "2025-04-12 17:02:53",
    "hash": "ad39f1cef0530b4bfe43997bcb816999"
  },
  {
    "title": "加蓬举行总统选举",
    "content": "【加蓬举行总统选举】财联社4月12日电，加蓬于当地时间4月12日举行总统选举，共有4名候选人获得参选资格，包括加蓬过渡总统恩圭马和前总理比利.比.恩泽等。投票于当天上午7时开始，至当天18时结束，在该国九个省的投票站同步进行。根据加蓬选举法规定，所有成年公民均须参与投票。",
    "date": "2025-04-12",
    "time": "15:26:34",
    "datetime": "2025-04-12 15:26:34",
    "fetch_time": "2025-04-12 17:02:53",
    "hash": "c937be2c0beadf8828683516f6d9c22d"
  },
  {
    "title": "江西省委金融办召开重点企业上市调度会",
    "content": "【江西省委金融办召开重点企业上市调度会】财联社4月12日电，为深入推进企业上市“映山红行动”升级工程，加快推动省内企业上市进程，4月11日，江西省委金融办召开重点企业上市调度会。会上，江西省3家在审企业负责人和证券机构项目负责人介绍了上市审核进展情况、存在的困难和问题。江西省委金融办常务副主任许忠华就企业提出的相关问题进行现场办公，就企业反映的相关诉求给予回应，对加快推动上市工作提出了明确要求。许忠华表示，各相关方面要强化问题导向，加强服务力量，形成工作合力；各地要加强与有关部门的对接沟通，加大企业问题协调帮扶力度；中介机构要强化保荐责任和专业服务；企业要会同中介机构对交易所提出的关注事项认真做好问询答复。据介绍，下一步，江西省委金融办将会同相关部门，加强与证监会、交易所沟通对接，一对一帮助指导在审企业解决上市堵点问题，推动在审企业加快上市进程。同时，进一步加大上市后备资源挖掘培育力度，举办江西资本市场高质量发展系列活动，持续纵深推进企业上市“映山红行动”升级工程，推动江西资本市场高质量发展。",
    "date": "2025-04-12",
    "time": "14:56:20",
    "datetime": "2025-04-12 14:56:20",
    "fetch_time": "2025-04-12 17:02:53",
    "hash": "2fe26c6a0a483285ab47cb4f47da6c07"
  },
  {
    "title": "伊朗外长已率团抵达阿曼 准备与美展开核谈判",
    "content": "【伊朗外长已率团抵达阿曼 准备与美展开核谈判】财联社4月12日电，记者获悉，当地时间12日，由伊朗外交部长阿拉格齐率领的伊朗代表团已抵达阿曼，将与美国举行核谈判。 (央视新闻)",
    "date": "2025-04-12",
    "time": "14:55:45",
    "datetime": "2025-04-12 14:55:45",
    "fetch_time": "2025-04-12 17:02:53",
    "hash": "aa5013961ee3cf0d8d4c150a578e1efc"
  },
  {
    "title": "深圳发布雷雨大风黄色和暴雨黄色预警",
    "content": "【深圳发布雷雨大风黄色和暴雨黄色预警】财联社4月12日电，深圳市气象台2025年04月12日14时35分发布全市暴雨黄色和雷雨大风黄色预警信号：目前深圳市有局地（雷）阵雨，预计未来2-3小时内受雷雨云团及冷空气前锋东移南压影响，深圳市雷阵雨趋于明显，最大小时雨强40毫米左右，雷雨云团过境后转冷空气大风降温过程，偏北最大阵风增大至10级左右。请落实各项防雨防风防雷电措施。",
    "date": "2025-04-12",
    "time": "14:49:58",
    "datetime": "2025-04-12 14:49:58",
    "fetch_time": "2025-04-12 17:02:53",
    "hash": "17894bc7f84aa251709a324ac8f0ea9a"
  },
  {
    "title": "滇港携手推动中药材全领域合作",
    "content": "【滇港携手推动中药材全领域合作】财联社4月12日电，滇港中医药全产业链发展推介会11日在云南昆明举行，200余名中医药界专家学者、企业家围绕中医药全产业链发展等议题，共话产业前景，推进滇港合作。云南被誉为“中药材宝库”，而香港是全球最大的中药材转口贸易中心。云南省委书记王宁在致辞中表示，希望滇港双方共同推进科技创新，促进中医药科技创新和产业创新深度融合；共同建设标准体系，让更多优质“云药”走进香港、走向世界；共同培育产业生态，共促香港企业家到云南投资发展；共同开拓海外市场，推动中医药国际化发展。中医药全产业链香港中心主席高永文认为，滇港两地中医药全产业链合作优势互补、潜力无限，希望双方强化资源精准对接，促进“种、科、工、贸”全产业链融合发展，助力云药提升品质、开拓市场，共同推动滇港中医药合作更进一步。香港中医中药界联合总会会长李应生表示，将携手云南为弘扬传播中医药文化、发展中医药产业作出不懈努力。会上，云南和香港有关单位和企业共签署11份合作协议及2份战略合作框架协议，旨在持续深化滇港中医药全领域合作，打造滇港中医药现代全产业链。",
    "date": "2025-04-12",
    "time": "14:48:02",
    "datetime": "2025-04-12 14:48:02",
    "fetch_time": "2025-04-12 17:02:53",
    "hash": "74874b51c22f8c692e1c208e5374da5d"
  },
  {
    "title": "中老铁路客货运输数据双双突破5000万",
    "content": "【中老铁路客货运输数据双双突破5000万】财联社4月12日电，自中老铁路的开通运营以来，客货运输数据双双突破了5000万，为促进中老两国人员往来、货物运输、人文交流注入了强劲动力。截至4月12日，中老铁路自开通运营以来，累计开行旅客列车7.4万列，发送旅客超5080万人次；开行货物列车5.3万列，累计运输货物突破5720万吨。两个“5000万”的突破，为客货运输、经贸和人文交流带来明显变化。",
    "date": "2025-04-12",
    "time": "14:47:08",
    "datetime": "2025-04-12 14:47:08",
    "fetch_time": "2025-04-12 17:02:53",
    "hash": "c7595ca940eb6c87416dd46b0731d611"
  },
  {
    "title": "乌称基辅遭俄无人机袭击致3人受伤",
    "content": "【乌称基辅遭俄无人机袭击致3人受伤】财联社4月12日电，乌克兰基辅市市长克利奇科当地时间4月12日通报称，当天凌晨，基辅市遭到俄军无人机袭击，由于被击落的俄军无人机碎片坠落导致该市民用基础设施遭到破坏，并造成至少3人受伤，袭击还引发了大规模火灾，救援人员已扑灭部分地区的火势。俄罗斯方面对此暂无回应。 (央视新闻)",
    "date": "2025-04-12",
    "time": "14:36:50",
    "datetime": "2025-04-12 14:36:50",
    "fetch_time": "2025-04-12 17:02:53",
    "hash": "a8a6818a6dcea9600c9bcd3bab83a0f2"
  },
  {
    "title": "截至今天14时 北京两大机场共取消航班693架次",
    "content": "【截至今天14时 北京两大机场共取消航班693架次】财联社4月12日电，从北京两大机场了解到，今天，首都机场和大兴机场，预计共执行航班1862架次，保障旅客超23万人次。航班执行方面，记者从首都机场了解到，截至今天14时，首都机场已执行269架次，取消429架次（含提前调减），大兴机场今天全天计划起降航班660架次，取消航班264架次（含提前调减）。目前，北京两大机场运行平稳。 (央视新闻)",
    "date": "2025-04-12",
    "time": "14:19:49",
    "datetime": "2025-04-12 14:19:49",
    "fetch_time": "2025-04-12 17:02:53",
    "hash": "53e3d0eb34144059a1c14af1bbba58a2"
  },
  {
    "title": "俄外交官：俄与欧盟及北约发生直接冲突可能性很小",
    "content": "【俄外交官：俄与欧盟及北约发生直接冲突可能性很小】财联社4月12日电，据塔斯社当地时间11日报道，俄罗斯常驻维也纳国际组织代表乌里扬诺夫当天表示，俄罗斯与欧盟以及北约发生直接冲突的可能性很小。乌里扬诺夫说，与俄罗斯进行直接对抗并不符合西方国家的利益。目前没有任何迹象表明俄罗斯与欧盟及北约会发生直接对抗，同时，欧盟也缺乏相应的政治意愿。 (央视新闻)",
    "date": "2025-04-12",
    "time": "14:15:21",
    "datetime": "2025-04-12 14:15:21",
    "fetch_time": "2025-04-12 17:02:53",
    "hash": "07e4afb20765986d926f9454bbffe807"
  },
  {
    "title": "",
    "content": "财联社4月12日电，中国地震台网正式测定：04月12日11时47分在巴布亚新几内亚附近海域（南纬4.80度，东经152.90度）发生6.0级地震，震源深度50千米。",
    "date": "2025-04-12",
    "time": "12:14:42",
    "datetime": "2025-04-12 12:14:42",
    "fetch_time": "2025-04-12 12:21:38",
    "hash": "80e89d5adedf60bcc02887d22ea0fc4c"
  },
  {
    "title": "特朗普拟腰斩NASA科学预算 马斯克公开呛声",
    "content": "【特朗普拟腰斩NASA科学预算 马斯克公开呛声】财联社4月12日电，据《日本经济新闻》网站4月12日报道，特朗普政府正考虑将2026年度美国国家航空航天局（NASA）科学预算削减一半。该科学预算主要用于望远镜开发等领域，预计目前的73亿美元预算将减至39亿美元。美国太空探索技术公司（SpaceX）创始人埃隆·马斯克11日在社交平台上发文称“此举令人担忧”，表达了不满。 (参考消息)",
    "date": "2025-04-12",
    "time": "12:08:12",
    "datetime": "2025-04-12 12:08:12",
    "fetch_time": "2025-04-12 12:11:37",
    "hash": "cd81d7ddd451eec04595ecf5adc3558d"
  },
  {
    "title": "海南洋浦区域国际集装箱枢纽港首个20万吨级泊位投用",
    "content": "【海南洋浦区域国际集装箱枢纽港首个20万吨级泊位投用】财联社4月12日电，载有1100余个集装箱的“博亚厦门”轮4月11日顺利停靠海南洋浦区域国际集装箱枢纽港扩建工程（一阶段）一期4#泊位，标志着该港口新增的1个15万吨级和1个20万吨级泊位投入运营。海南洋浦区域国际集装箱枢纽港扩建工程（一阶段）一期新增的4#和5#泊位是洋浦国际集装箱码头建设“双向双枢纽港”的重点项目，承载着服务西部陆海新通道建设、海南自由贸易港建设的重要使命。两个集装箱泊位使用深水岸线700米，年设计吞吐量200万标箱。",
    "date": "2025-04-12",
    "time": "12:00:13",
    "datetime": "2025-04-12 12:00:13",
    "fetch_time": "2025-04-12 12:01:37",
    "hash": "d2bed3954cce4609bc9e0166fe653000"
  },
  {
    "title": "受外来沙尘传输影响 上海今天下午至明天上午将出现PM₁₀污染",
    "content": "【受外来沙尘传输影响 上海今天下午至明天上午将出现PM₁₀污染】财联社4月12日电，“上海环境”官微12日上午发布消息称，受外来沙尘输送影响，预计4月12日下午至13日上午，上海市将受到沙尘输送过境影响，出现PM10中度及以上污染过程。沙尘污染期间，提示广大市民应减少外出，避免暴露，如需外出请做好个人防护措施；特殊人群（如儿童、老人、孕妇、慢性病患者）应避免户外活动，易感人群需特别注意防护。",
    "date": "2025-04-12",
    "time": "11:57:31",
    "datetime": "2025-04-12 11:57:31",
    "fetch_time": "2025-04-12 12:01:37",
    "hash": "a84184e808bf5026cfec5c2418aae0c5"
  },
  {
    "title": "美媒：美国海关关税系统故障持续超10小时 目前已恢复运行",
    "content": "【美媒：美国海关关税系统故障持续超10小时 目前已恢复运行】财联社4月12日电，据美国全国广播公司商业频道(CNBC)报道，当地时间11日，美国海关和边境保护局发布警报，告知用户其用于豁免货运关税的系统出现故障。据报道，根据该机构发布的最新警报，故障持续了10多个小时，目前已恢复运行。受影响的货运包括现在处于特朗普政府实施的90天关税暂停期内的国家的所有贸易货物。 (中新网)",
    "date": "2025-04-12",
    "time": "11:54:30",
    "datetime": "2025-04-12 11:54:30",
    "fetch_time": "2025-04-12 12:01:37",
    "hash": "a62b786a7f11a6bdaddace79229d6eab"
  },
  {
    "title": "美关税系统突发故障 持续超10小时方才恢复",
    "content": "【美关税系统突发故障 持续超10小时方才恢复】财联社4月12日电，美国海关和边境保护局当地时间4月11日发布警报，称该部门一个涉及关税豁免的代码出现故障。海关与边境保护局表示，这一故障在持续了超过10个小时后被修复。据悉，出现故障的代码可以豁免本周所有不应受到特朗普政府关税新政策影响的在途货物。故障发生时，美国海关的“自动商业环境”系统无法对在4月9日以后提交申请的、符合在途条件的货物适用较低的10%税率。美国多位进口商表示，很多进口商难以“弄清楚新关税何时实施”并制定相应计划。在关税政策引发不确定性和担忧的大背景下，此事是对美国货主和供应链的最新打击。外界也由此质疑美国海关是否有能力落实特朗普的关税新政。 (央视新闻)",
    "date": "2025-04-12",
    "time": "11:54:30",
    "datetime": "2025-04-12 11:54:30",
    "fetch_time": "2025-04-12 12:11:37",
    "hash": "9413f477797868041940a8804c920c29"
  },
  {
    "title": "国内首个 中国电科产业基础研究院研发金刚石氮空位色心微波激射器",
    "content": "【国内首个 中国电科产业基础研究院研发金刚石氮空位色心微波激射器】财联社4月12日电，据中国电科官微，近日，中国电科产业基础研究院科研团队联合中国科学院科研团队，成功研发高灵敏度集成金刚石氮空位色心量子磁强计和国内首个金刚石氮空位色心微波激射器。“金刚石氮空位色心这一固态量子自旋体系，具有易于初始化和读出、可操控、较长相干时间等优点，在量子精密测量、量子计算等领域具有巨大应用前景。”产业基础研究院科研团队技术专家表示，经过多年攻坚，他们成功研发集成金刚石量子磁传感器灵敏度达到国际先进水平，金刚石氮空位色心微波激射器最大量子震荡功率达到国际领先水平。后续，技术团队将进一步推进传感器性能提升与集成，推动基于固态自旋体系量子传感器产业化落地，应用于工业探伤、地质学资源勘查、深空通信、生物学检测、材料研究等领域。",
    "date": "2025-04-12",
    "time": "11:49:18",
    "datetime": "2025-04-12 11:49:18",
    "fetch_time": "2025-04-12 11:51:36",
    "hash": "d57757c25061d4fdb08511ec18bdf4c6"
  },
  {
    "title": "中国电科产业基础研究院研发金刚石氮空位色心微波激射器",
    "content": "【中国电科产业基础研究院研发金刚石氮空位色心微波激射器】财联社4月12日电，据中国电科官微，近日，中国电科产业基础研究院科研团队联合中国科学院科研团队，成功研发高灵敏度集成金刚石氮空位色心量子磁强计和国内首个金刚石氮空位色心微波激射器。“金刚石氮空位色心这一固态量子自旋体系，具有易于初始化和读出、可操控、较长相干时间等优点，在量子精密测量、量子计算等领域具有巨大应用前景。”产业基础研究院科研团队技术专家表示，经过多年攻坚，他们成功研发集成金刚石量子磁传感器灵敏度达到国际先进水平，金刚石氮空位色心微波激射器最大量子震荡功率达到国际领先水平。后续，技术团队将进一步推进传感器性能提升与集成，推动基于固态自旋体系量子传感器产业化落地，应用于工业探伤、地质学资源勘查、深空通信、生物学检测、材料研究等领域。",
    "date": "2025-04-12",
    "time": "11:49:18",
    "datetime": "2025-04-12 11:49:18",
    "fetch_time": "2025-04-12 12:01:37",
    "hash": "37a21cde6414e43b021f6c87c7017eb6"
  },
  {
    "title": "英德等国承诺为乌提供更多军事支持",
    "content": "【英德等国承诺为乌提供更多军事支持】财联社4月12日电，新一轮“乌克兰防务联络组织”会议当地时间4月11日在布鲁塞尔举行，约50个国家的代表出席会议，乌克兰总统泽连斯基和美国国防部长赫格塞思以线上方式参加会议。会议承诺向乌克兰提供总额超210亿欧元的军事支持，包括英国今年承诺的45亿英镑和德国提供的110亿欧元。德国国防部长皮斯托里乌斯表示，德国将向乌克兰提供包括4套IRIS-T防空系统在内的多种武器。泽连斯基敦促与会国向乌克兰提供更多防空系统，乌克兰希望能获得至少10套“爱国者”反导系统。 (CCTV国际时讯)",
    "date": "2025-04-12",
    "time": "11:48:08",
    "datetime": "2025-04-12 11:48:08",
    "fetch_time": "2025-04-12 11:51:36",
    "hash": "c8793dc868af4e7c7cfa6f86deb1cfbe"
  },
  {
    "title": "郑州机场个别航班取消或延误",
    "content": "【郑州机场个别航班取消或延误】财联社4月12日电， 12日早上，郑州机场的平均风速约11-12米/秒，阵风17-20米/秒。为应对大风天气，郑州机场发布大风黄色预警，各保障单位全力做好大风天气下的航班保障工作以及旅客服务工作，至上午9时30分左右，郑州机场运行安全有序。根据航班计划，今天郑州机场将执行航班464架次，至上午9点半，已执行42架次，其中自郑州机场起飞的航班有30架次。另外，郑州至呼和浩特、桂林至郑州、温州至郑州等三个航班取消，有郑州至上海、喀什，沈阳至郑州等5个航班延误。",
    "date": "2025-04-12",
    "time": "11:35:38",
    "datetime": "2025-04-12 11:35:38",
    "fetch_time": "2025-04-12 11:41:36",
    "hash": "2f55594c7b502cfe0ca6c291f0032a85"
  },
  {
    "title": "蚂蚁集团副总裁、前基础大模型负责人徐鹏离职",
    "content": "【蚂蚁集团副总裁、前基础大模型负责人徐鹏离职】财联社4月12日电，蚂蚁集团副总裁、前基础大模型负责人徐鹏已离职。徐鹏一直从事人工智能领域技术研究，曾在谷歌工作11年，负责和领导了谷歌翻译的核心技术研发，并参与了谷歌显示广告系统的算法研发。此前蚂蚁成立AI创新研发与应用部门NextEvo，由徐鹏担任负责人，承担了蚂蚁AI的所有核心技术研发，包括蚂蚁百灵大模型的所有研发工作。（记者 黄心怡）",
    "date": "2025-04-12",
    "time": "11:31:10",
    "datetime": "2025-04-12 11:31:10",
    "fetch_time": "2025-04-12 11:31:36",
    "hash": "d740e169f7904abb92a51680b83347d3"
  },
  {
    "title": "大风南界抵达湖北至江苏北部一带 华北等地阵风具有极端性",
    "content": "【大风南界抵达湖北至江苏北部一带 华北等地阵风具有极端性】财联社4月12日电，昨天（4月11日）到今晨，我国多地出现8至10级大风，局地阵风14级以上。今天8时，6级以上大风的南界已经抵达湖北、湖南北部、安徽、江苏北部一带。周末两天，中东部多地大风持续，其中今天华北、黄淮等地阵风具有极端性，公众请做好防范措施，非必要不外出。",
    "date": "2025-04-12",
    "time": "11:29:43",
    "datetime": "2025-04-12 11:29:43",
    "fetch_time": "2025-04-12 11:31:36",
    "hash": "907dc7ec29f012bfba21036846984086"
  },
  {
    "title": "荷兰国防大臣：美国不再主导“乌克兰防务联络小组”",
    "content": "【荷兰国防大臣：美国不再主导“乌克兰防务联络小组”】财联社4月12日电，据欧洲新闻电视台11日报道，在美国特朗普政府释放一系列信号，表明美国正在弱化其在北约所担任角色的背景下，荷兰国防大臣吕本·布雷克尔曼斯告诉该媒体，美国不再主导“乌克兰防务联络小组”（UDCG），英德两国目前已接替主导这一小组事务的角色。 (环球网)",
    "date": "2025-04-12",
    "time": "11:21:18",
    "datetime": "2025-04-12 11:21:18",
    "fetch_time": "2025-04-12 11:21:35",
    "hash": "6f7f1ada14a18dd5b2dcce6eb3a09724"
  },
  {
    "title": "上海航交所：船舶周转率下降 沿海散货综合指数走势平稳",
    "content": "【上海航交所：船舶周转率下降 沿海散货综合指数走势平稳】财联社4月12日电，上海航运交易所4月12日发布的中国沿海(散货)运输市场周度报告显示，本周，华南线价格依旧坚挺，华东线运价略有上浮。叠加周末两天大风来袭，船舶提前避风，影响周转，沿海散货综合指数走势平稳。4月11日，上海航运交易所发布的中国沿海（散货）综合运价指数报收1044.45点，较上期上涨0.2%。",
    "date": "2025-04-12",
    "time": "11:17:53",
    "datetime": "2025-04-12 11:17:53",
    "fetch_time": "2025-04-12 11:18:18",
    "hash": "deade740b1c8abac812bad107183aac3"
  },
  {
    "title": "百亿基金经理鲍无可在管4只产品增聘新人",
    "content": "【百亿基金经理鲍无可在管4只产品增聘新人】财联社4月12日电，又有百亿基金经理旗下多只产品“共管。景顺长城基金今日连发4则公告显示，鲍无可在管的景顺长城价值稳进三年定期开放、景顺长城国企价值混合、景顺长城沪港深精选、景顺长城价值发现混合4只基金增聘基金经理，4只基金增聘基金经理分别为刘苏、邹立虎、张仲维、王勇。鲍无可是市场较为强调安全边际的价值投资选手，风格均衡，看重绝对收益。2009年加入景顺长城，当前资管规模为177.83亿元，在管最佳任期回报为366.67%。（财联社记者 闫军）",
    "date": "2025-04-12",
    "time": "11:12:29",
    "datetime": "2025-04-12 11:12:29",
    "fetch_time": "2025-04-12 11:13:39",
    "hash": "d76451236552144982d7f9eb8c1b6122"
  },
  {
    "title": "百亿基金经理鲍无可在管4只产品增聘",
    "content": "【百亿基金经理鲍无可在管4只产品增聘】财联社4月12日电，又有百亿基金经理旗下多只产品“共管。景顺长城基金今日连发4则公告显示，鲍无可在管的景顺长城价值稳进三年定期开放、景顺长城国企价值混合、景顺长城沪港深精选、景顺长城价值发现混合4只基金增聘基金经理，4只基金增聘基金经理分别为刘苏、邹立虎、张仲维、王勇。鲍无可是市场较为强调安全边际的价值投资选手，风格均衡，看重绝对收益。2009年加入景顺长城，当前资管规模为177.83亿元，在管最佳任期回报为366.67%。（财联社记者 闫军）",
    "date": "2025-04-12",
    "time": "11:12:29",
    "datetime": "2025-04-12 11:12:29",
    "fetch_time": "2025-04-12 11:41:36",
    "hash": "35a618ff6688755a7225e8a390af1883"
  },
  {
    "title": "受大风极端天气影响 国铁北京局多趟列车停运",
    "content": "【受大风极端天气影响 国铁北京局多趟列车停运】财联社4月12日电，从国铁北京局了解到，为确保旅客列车运行安全，经与气象专家会商，国铁北京局根据大风极端天气影响范围，4月12日将对京张高铁、京津城际、京沪高铁、京广高铁、京哈高铁、石太客专和山区普速铁路部分旅客列车采取临时停运措施。12日京包客专全线临时停运。13日将对京张高铁和山区普速铁路部分旅客列车采取临时停运措施。",
    "date": "2025-04-12",
    "time": "11:03:22",
    "datetime": "2025-04-12 11:03:22",
    "fetch_time": "2025-04-12 11:04:56",
    "hash": "ab25f30e6bca33983a02fcd45512711b"
  },
  {
    "title": "洪都拉斯外长：尼加拉瓜将派驻新任驻洪大使",
    "content": "【洪都拉斯外长：尼加拉瓜将派驻新任驻洪大使】财联社4月12日电，洪都拉斯外长雷纳当地时间11日在接受媒体采访时表示，他已经致电尼加拉瓜外长，尼方并没有撤回驻洪大使，只是正常的大使更替而已，并不是如外界所传的因为对拉共体峰会的共识不满而撤回大使。记者获悉，尼加拉瓜联合总统穆里略已经宣布将任命达令·里奥斯为新任驻洪都拉斯大使，里奥斯目前已经抵达洪都拉斯，目前为公使衔参赞，将成为大使。11日早些时候，尼加拉瓜政府发布公告，宣布撤回尼驻洪大使和驻特古西加尔巴总领事，引多方关注。",
    "date": "2025-04-12",
    "time": "11:02:16",
    "datetime": "2025-04-12 11:02:16",
    "fetch_time": "2025-04-12 11:02:26",
    "hash": "5389282142857d4e878eff5e04ba0651"
  },
  {
    "title": "大风等强对流天气来袭 广东浙江多条水上客运航线停航",
    "content": "【大风等强对流天气来袭 广东浙江多条水上客运航线停航】财联社4月12日电，从交通运输部海事局了解到，受较强冷空气影响，今天，广东、浙江沿海地区迎来大风、强对流天气，多条水上客运航线停航。受冷空气及西南暖湿气流共同影响，今天广东珠江口水域短时阵风将达8~10级，珠江口多条水上客运航线停航。其中，广州琶洲、南沙口岸的港澳客运航线停航；珠海海岛游、香港航线、市际航线停航；中山至澳门、深圳的航线停航；东莞到香港、珠海桂山、东澳的航线停航；江门川山群岛海上客运航线停航。复航时间将视天气变化情况而定。同样受较强冷空气影响，今天浙江沿海已出现10级大风，水上客渡运航线停航80条，舟山水域71条水上客运航线全部停航。舟山海事部门还协调重点旅游水上客运航线疏客工作。目前，普陀山景区已紧急疏散旅客超3.2万人次。财联社4月12日电，",
    "date": "2025-04-12",
    "time": "11:00:50",
    "datetime": "2025-04-12 11:00:50",
    "fetch_time": "2025-04-12 11:02:26",
    "hash": "719088f493bb171941244e67367be32e"
  },
  {
    "title": "受大雾和大风影响 福建沿海66条客渡运航线停航",
    "content": "【受大雾和大风影响 福建沿海66条客渡运航线停航】财联社4月12日电，今天早晨到上午，福建沿海多地出现大雾天气。受大雾和大风天气共同影响，为了确保安全，截至12日10时，福建沿海共有66条客渡运航线、162艘客渡船停航，其中4条两岸“小三通”客运航线全部停航，湄洲岛轮渡、厦漳轮渡等多条大客流航线停航。此外，福建沿海96个水上施工作业项目已全部停工。",
    "date": "2025-04-12",
    "time": "10:58:21",
    "datetime": "2025-04-12 10:58:21",
    "fetch_time": "2025-04-12 11:02:26",
    "hash": "0c6fbe8f07b53cfe53f976ce60c8c5d3"
  },
  {
    "title": "护盘资金单周净流入近1700亿 4只沪深300ETF占近千亿",
    "content": "【护盘资金单周净流入近1700亿 4只沪深300ETF占近千亿】财联社4月12日电，A股在政策呵护、资金大举买入之下迅速修复了关税带来的悲观情绪。本周（4月7日-11日）股票ETF获得巨量买入，合计资金净流入达到1697.17亿元，7只宽基ETF净流入超百亿。其中，4只头部沪深300ETF资金净流入居前，合计净流入983亿元，占比近58%。华泰柏瑞沪深300ETF资金净流入最高，为339.54亿元，易方达沪深300ETF和华夏沪深300ETF净流入分别为246亿元、240.6亿元，嘉实沪深300ETF净流入157亿元。此外，还有包括南方中证500ETF、南方中证1000ETF和华夏上证50ETF合计净流入超百亿。（财联社记者 闫军）",
    "date": "2025-04-12",
    "time": "10:57:44",
    "datetime": "2025-04-12 10:57:44",
    "fetch_time": "2025-04-12 11:02:26",
    "hash": "654aca589e780fd4307cc50a587bc806"
  },
  {
    "title": "中央气象台4月12日10时发布暴雪橙色预警",
    "content": "【中央气象台4月12日10时发布暴雪橙色预警】财联社4月12日电，中央气象台4月12日10时发布暴雪橙色预警：预计4月12日14时至4月13日14时，内蒙古东部、辽宁东北部、吉林中东部、黑龙江西北部以及西藏东北部、川西高原中部等地有大到暴雪，其中，内蒙古东部、辽宁东北部、吉林东部等地部分地区有大暴雪，局地特大暴雪（30～38毫米）；上述地区新增积雪深度3～15厘米，局地可达30厘米左右。",
    "date": "2025-04-12",
    "time": "10:44:50",
    "datetime": "2025-04-12 10:44:50",
    "fetch_time": "2025-04-12 10:45:55",
    "hash": "ecd75c7ff9046d94aa9c5a1e992938ae"
  },
  {
    "title": "中国国产飞机C909老挝商业首航仪式在万象举行",
    "content": "【中国国产飞机C909老挝商业首航仪式在万象举行】财联社4月12日电，老挝航空C909客机当地时间12日上午举行首航仪式。该航班从老挝首都万象瓦岱国际机场起飞，目的地为老挝南部城市巴瑟，航班号为QV331。这架飞机是上个月由中国商飞公司向老挝航空公司交付的首架C909飞机，这也是中国的喷气式客机首次进入老挝市场。",
    "date": "2025-04-12",
    "time": "10:35:32",
    "datetime": "2025-04-12 10:35:32",
    "fetch_time": "2025-04-12 10:45:55",
    "hash": "3c2e531781c21b8ac5010a8d2e4e8bfb"
  },
  {
    "title": "受大风影响 天津海事局实施水上交通管制",
    "content": "【受大风影响 天津海事局实施水上交通管制】财联社4月12日电，天津港水域4月12日凌晨风力达到9级。为确保船舶航行安全，天津海事局实施水上交通管制措施，自4月12日01:45起暂停船舶进出港、移泊。海事部门提醒：管制期间，请各有关船舶加强值守，保持甚高频有效收听，锚泊船舶，加强瞭望，勤测锚位，与附近船舶保持足够安全距离，防止走锚发生事故。",
    "date": "2025-04-12",
    "time": "10:33:08",
    "datetime": "2025-04-12 10:33:08",
    "fetch_time": "2025-04-12 10:45:55",
    "hash": "b9d274f7112fd59da4284cf893f79c89"
  },
  {
    "title": "大风沙尘天气造成106个路段出行受影响",
    "content": "【大风沙尘天气造成106个路段出行受影响】财联社4月12日电，从交通运输部路网中心了解到，截至4月12日7时，因大风沙尘，北京、河北、山西、内蒙古、河南、陕西、甘肃、新疆8省（区、市）受影响路段106个（涉及82条高速公路）：主线封闭路段16个；单独关闭收费站503个（主线可通行），恢复通行时间待定。因降雨，湖南单独关闭收费站22个（涉及8条高速公路，主线可通行），预计今日下午恢复通行。因降雪，内蒙古单独关闭收费站90个（涉及9条高速公路、4条普通国道，主线可通行），恢复通行时间待定。",
    "date": "2025-04-12",
    "time": "10:30:34",
    "datetime": "2025-04-12 10:30:34",
    "fetch_time": "2025-04-12 10:45:55",
    "hash": "285821037b57985174dafc1a254e498b"
  },
  {
    "title": "近岸海域将出现中浪到大浪",
    "content": "【近岸海域将出现中浪到大浪】财联社4月12日电，记者从自然资源部获悉，受出海气旋与较强冷空气的共同影响，渤海、黄海、东海仍将出现大浪到巨浪过程，近岸海域将出现中浪到大浪。国家海洋预报台今天（12日）早上继续发布海浪蓝色警报：预计4月12日中午到13日中午，渤海、黄海、东海将出现2.5到4.5米的大浪到巨浪区；辽宁南部、河北、山东北部、东部、江苏、上海、浙江北部近岸海域将出现2到3.4米的中浪到大浪，近岸海域海浪预警级别为蓝色。提醒在这些海域作业的船只要注意安全，沿海各有关单位要提前采取防浪避浪措施。 (央视新闻)",
    "date": "2025-04-12",
    "time": "10:28:51",
    "datetime": "2025-04-12 10:28:51",
    "fetch_time": "2025-04-12 10:45:55",
    "hash": "9b3d05911aa417595160c2da766bb671"
  },
  {
    "title": "工信部副部长辛国斌会见英国商业贸易部国务大臣道格拉斯·亚历山大",
    "content": "【工信部副部长辛国斌会见英国商业贸易部国务大臣道格拉斯·亚历山大】财联社4月12日电，工业和信息化部副部长辛国斌4月11日在北京会见英国商业贸易部国务大臣道格拉斯·亚历山大，双方就进一步深化产业合作进行交流。辛国斌表示，工业和信息化部愿同英方一道落实好两国元首通话达成的重要共识，深化汽车、绿色低碳、数字经济、人工智能等领域合作，高水平打造中英现代产业合作伙伴关系，推动形成更多合作成果，实现共同发展。道格拉斯·亚历山大表示，愿与中方共同努力，推动举办第二次中英产业合作对话，加强产业战略对接，拓展合作深度和广度，共享发展成果。",
    "date": "2025-04-12",
    "time": "10:25:43",
    "datetime": "2025-04-12 10:25:43",
    "fetch_time": "2025-04-12 10:45:55",
    "hash": "4c52400000f871099c3285aa62678ea5"
  },
  {
    "title": "财联社创投通：一级市场本周融资总额约35.79亿元环比减少56.73% 先进制造、医疗健康活跃度居前",
    "content": "【财联社创投通：一级市场本周融资总额约35.79亿元环比减少56.73% 先进制造、医疗健康活跃度居前】《科创板日报》12日讯，据财联社创投通数据显示，本周（4.5-4.11）国内统计口径内共发生71起投融资事件，较上周66起增加7.58%；已披露的融资总额合计约35.79亿元，较上周82.71亿元减少56.73%。从投资事件数量来看，先进制造、医疗健康、集成电路、传统工业、新材料、汽车出行等领域较活跃；从融资总额来看，先进制造披露的融资总额最多，约11.30亿元。爱芯元智完成由宁波通商基金、镇海产投、重庆产业投资母基金、重庆两江基金、元禾璞华、韦豪创芯等机构参与的超10亿元C轮融资，为本周披露金额最高的投资事件。",
    "date": "2025-04-12",
    "time": "10:17:17",
    "datetime": "2025-04-12 10:17:17",
    "fetch_time": "2025-04-12 10:45:55",
    "hash": "0535a1b0a9f2e9f51b5d124cf907b12a"
  },
  {
    "title": "",
    "content": "财联社4月12日电，韩国首尔市长吴世勋将不参加韩国总统竞选。",
    "date": "2025-04-12",
    "time": "10:16:46",
    "datetime": "2025-04-12 10:16:46",
    "fetch_time": "2025-04-12 10:45:55",
    "hash": "c1e490d38dd5bc0d430fcc5e88388920"
  },
  {
    "title": "中国贸促会副会长陈建安会见西班牙企业家组织联合会国际关系部主席玛尔塔·布兰科一行",
    "content": "【中国贸促会副会长陈建安会见西班牙企业家组织联合会国际关系部主席玛尔塔·布兰科一行】财联社4月12日电，中国贸促会副会长陈建安4月11日在京会见西班牙企业家组织联合会国际关系部主席玛尔塔·布兰科及西班牙商会总经理伊玛库拉达·里埃拉，双方就深化中西企业交流、加强机构合作和参与第三届链博会等议题交换意见。",
    "date": "2025-04-12",
    "time": "10:10:24",
    "datetime": "2025-04-12 10:10:24",
    "fetch_time": "2025-04-12 10:45:55",
    "hash": "89396726045c3967a28c3815c50c9277"
  },
  {
    "title": "受大风天气影响 经张大高铁、石太客专等线部分列车停运",
    "content": "【受大风天气影响 经张大高铁、石太客专等线部分列车停运】财联社4月12日电，受较强冷空气影响，国铁太原局管内经张大高铁、石太客专等线部分列车停运，保障安全。受大风天气影响停运列车涉及线路包括张大高铁、石太客专及京原线、阳涉线、京包线等普速线路，主要集中在往返北京方面。其中，张大高铁停运14对，石太客专停运18.5对；京原线停运2对。另外，太兴线、太焦线、宁岢线等线路运行的部分列车也将停运。",
    "date": "2025-04-12",
    "time": "10:09:35",
    "datetime": "2025-04-12 10:09:35",
    "fetch_time": "2025-04-12 10:45:55",
    "hash": "b886f418c27cb63220ae24b158eeb5e4"
  },
  {
    "title": "中央气象台4月12日10时发布强对流天气蓝色预警",
    "content": "【中央气象台4月12日10时发布强对流天气蓝色预警】财联社4月12日电，中央气象台4月12日10时发布强对流天气蓝色预警，预计4月12日14时至13日14时，华南南部等地的部分地区将有8级以上雷暴大风或冰雹天气，其中，福建东南部、广东中南部等地的部分地区将有10级以上雷暴大风，最大风力可达11级以上;华南南部、西南地区南部等地的部分地区将有小时雨量大于20毫米的短时强降水天气，其中，福建东南部、广东南部等地的部分地区小时雨量大于50毫米，最大可达60毫米以上。预计，强对流的主要影响时段为今天午后。",
    "date": "2025-04-12",
    "time": "10:05:01",
    "datetime": "2025-04-12 10:05:01",
    "fetch_time": "2025-04-12 10:45:55",
    "hash": "596b309e0c2571cdd07c93c30772a256"
  },
  {
    "title": "韩国民调显示李在明参选领先优势扩大",
    "content": "【韩国民调显示李在明参选领先优势扩大】财联社4月12日电，韩国一项最新民意调查结果显示，下届总统热门人选、最大在野党共同民主党前党首李在明以37%的支持率继续领跑，领先优势扩大。民调机构“盖洛普韩国”8日至10日就总统选举相关话题对1005名韩国成年人展开民意调查。这是尹锡悦被罢免总统职务以来，该机构实施的首次民调。11日发布的调查结果显示，李在明以37%的支持率排名第一，为其今年以来所获最高支持率，比上周民调所得34%上升3个百分点。",
    "date": "2025-04-12",
    "time": "10:03:42",
    "datetime": "2025-04-12 10:03:42",
    "fetch_time": "2025-04-12 10:45:55",
    "hash": "7ed685e06027d589d18ee258d732362c"
  },
  {
    "title": "今年我国快递业务量已突破500亿件",
    "content": "【今年我国快递业务量已突破500亿件】财联社4月12日电，从国家邮政局了解到，截至4月11日，今年我国快递业务量已突破500亿件，比2024年提前了18天。今年以来，邮政、快递企业积极探索“共同配送”“客货邮”等融合发展模式，因地制宜完善县、乡、村三级寄递物流网络节点建设。",
    "date": "2025-04-12",
    "time": "10:00:06",
    "datetime": "2025-04-12 10:00:06",
    "fetch_time": "2025-04-12 10:45:55",
    "hash": "07c946d063595a5bf70d0132d47f8b1f"
  },
  {
    "title": "金砖国家召开经贸联络组第二次会议，强调共同维护多边贸易体制，反对单边主义和贸易保护主义",
    "content": "【金砖国家召开经贸联络组第二次会议，强调共同维护多边贸易体制，反对单边主义和贸易保护主义】财联社4月12日电，4月10—11日，2025年金砖国家经贸联络组第二次会议以视频形式举行。会上，金砖成员专门就美“对等关税”政策深入交换意见，对相关措施引发的贸易紧张局势表示严正关切，并呼吁共同反对单边主义和贸易保护主义。中方指出，近期，美国政府推出“对等关税”政策，严重破坏国际贸易体系，扰乱全球产业链供应链，对世界经济造成持续冲击，是典型的单边主义、保护主义和经济霸凌行径。金砖国家是新兴市场国家和发展中国家加强团结合作、维护共同利益的重要平台，在推动全球治理体系改革、推进全球贸易投资自由化便利化进程中发挥着重要作用。在此特殊时期，金砖成员更要坚持全球化的正确方向，共同维护以规则为基础的多边贸易体制，维护全球经济稳定。金砖成员高度关注美“对等关税”对多边贸易体制构成严重冲击。多个成员指出“对等关税”严重违反世贸组织规则，是单边主义、保护主义行为，将严重影响全球经济增长，损害广大发展中国家利益。金砖国家应加强团结，就此向世界发出共同声音。各方将继续在经贸渠道就应对美“对等关税”问题深入交换意见，加强立场协调，坚守和维护以规则为基础的多边贸易体制，共同应对当前全球贸易紧张局势。会上，各方还围绕制定《金砖国家经济伙伴战略2030》、数据经济合作、维护多边贸易体制等议题进行讨论，为5月金砖国家经贸部长会议和7月金砖国家领导人会晤做好经贸成果准备。",
    "date": "2025-04-12",
    "time": "09:40:06",
    "datetime": "2025-04-12 09:40:06",
    "fetch_time": "2025-04-12 10:45:55",
    "hash": "56ae631a7dabedb105d2c7b1fc0ca177"
  },
  {
    "title": "截至9时 首都机场今天已取消航班413架次",
    "content": "【截至9时 首都机场今天已取消航班413架次】财联社4月12日电，记者从首都机场了解到，根据气象消息，首都机场今天白天到夜间，西北风6~7级，阵风8~9级。预计12时至20时，西北风7~8级，阵风9~11级。首都机场今天全天计划起降航班1202架次，运送旅客12.9万人次，截至今天9时，已执行192架次，取消413架次（含提前调减）。目前首都机场运行平稳。 (央视新闻)",
    "date": "2025-04-12",
    "time": "09:37:12",
    "datetime": "2025-04-12 09:37:12",
    "fetch_time": "2025-04-12 10:45:55",
    "hash": "db73374ed24ee011d12aed787140f5a6"
  },
  {
    "title": "中信证券：物理AI加速智驾与人形机器人产业变革",
    "content": "【中信证券：物理AI加速智驾与人形机器人产业变革】财联社4月12日电，中信证券研报表示，Cosmos+Ominiverse有望加速物理AI发展，料将带动智能驾驶以及人形机器人行业的发展。通过复盘CAE软件以及CUDA生态发展历程，我们认为仿真以及开发工具的迭代可直接加速相关行业的发展节奏，缩短行业的研发生产周期，降低工程实现门槛，最终将降本传导至终端产品研发制造环节。展望未来，我们认为Cosmos+Ominiverse的组合有望复刻CAE以及CUDA加速制造业和AI发展的效果，赋能智能驾驶以及人形机器人行业进入新发展阶段。因此，我们建议关注三条投资主线：1）Cosmos+Ominiverse硬件供应商；2）智能驾驶及人形机器人产业链；3）智能驾驶及人形机器人主机厂。",
    "date": "2025-04-12",
    "time": "09:36:37",
    "datetime": "2025-04-12 09:36:37",
    "fetch_time": "2025-04-12 10:45:55",
    "hash": "e87bc3571da4183eea998cb3409352b9"
  },
  {
    "title": "",
    "content": "财联社4月12日电，国际货币基金组织（IMF）执董会批准为阿根廷提供为期48个月、200亿美元的延期安排；阿根廷新计划的首次资金拨付将达120亿美元。美洲开发银行宣布为阿根廷提供100亿美元的一揽子支持计划。",
    "date": "2025-04-12",
    "time": "09:26:02",
    "datetime": "2025-04-12 09:26:02",
    "fetch_time": "2025-04-12 10:45:55",
    "hash": "6a40f17e44d1aa3cb2eb8822a662184b"
  },
  {
    "title": "",
    "content": "财联社4月12日电，币安在与特朗普加密公司谈判时寻求限制美国监管；还一直在与世界自由金融公司就推出一种新的与美元挂钩的加密货币进行谈判。",
    "date": "2025-04-12",
    "time": "09:17:53",
    "datetime": "2025-04-12 09:17:53",
    "fetch_time": "2025-04-12 10:45:55",
    "hash": "69fd84ac5cb7d18d7cd36d04e6b3fb3d"
  },
  {
    "title": "郑州市继续发布大风黄色预警信号",
    "content": "【郑州市继续发布大风黄色预警信号】财联社4月12日电，郑州市气象台2025年04月12日08时55分继续发布大风黄色预警信号：11日夜里我市出现大风天气，平均风力7-8级，最大阵风11级，出现在北龙湖，此次大风天气具有一定极端性。预计今天白天郑州市主城区、航空港区、上街区所辖乡镇及街道有5到6级西北风，阵风8到9级，局地10级以上，并伴有浮尘或扬沙。对农业生产、室外作业、电力通讯设施、文旅和户外活动等影响较大，请注意防范。",
    "date": "2025-04-12",
    "time": "09:10:32",
    "datetime": "2025-04-12 09:10:32",
    "fetch_time": "2025-04-12 10:45:55",
    "hash": "665f985c80fadb662756f9f70d08a713"
  },
  {
    "title": "雷雨大风已抵达广东韶关并逐步南下 红色预警发布",
    "content": "【雷雨大风已抵达广东韶关并逐步南下 红色预警发布】财联社4月12日电，广东韶关乐昌市4月12日早上受强对流云团影响，大源镇已出现12级以上阵风，并伴有强雷电和短时强降水，乐昌市气象台于当天7时12分将大源镇雷雨大风橙色预警信号升级为红色。这是本轮强对流天气广东首个发布的雷雨大风红色预警，预示强对流天气已抵达粤北将逐步南下。韶关市预警发布中心随后在上午8时前发布武江区、浈江区、翁源县、南雄市、仁化县、始兴县、曲江区雷雨大风橙色预警，预计未来1—2小时内将出现8—10级短时大风，并伴有强雷电。提醒人员切勿外出，确保留在最安全的地方；相关应急处置部门和抢险单位随时准备启动抢险应急方案等。",
    "date": "2025-04-12",
    "time": "09:09:41",
    "datetime": "2025-04-12 09:09:41",
    "fetch_time": "2025-04-12 10:45:55",
    "hash": "472cc17457a6bdc76f468938613fc577"
  }
]